{"login_history": [{"cookie_name": "*************************_Qu", "ip_address": "87.209.236.159", "language_code": "nl", "timestamp": "2020-10-08T11:39:49+00:00", "user_agent": "Instagram 162.0.0.42.125 Android (29/10; 420dpi; 1080x2081; motorola; moto g(8) plus; doha_n; qcom; nl_NL; 249507608)", "device_id": "android-b000b2ddffbfeef2"}], "registration_info": {"registration_username": "", "ip_address": "87.202.246.159", "registration_time": "2020-10-08T11:39:47+00:00", "registration_email": "blabla@kippietok.nl", "registration_phone_number": "", "device_name": ""}}